setup.py
mempy/__init__.py
mempy/harakisu.py
mempy/ichingbase.py
mempy/keymoon.py
mempy/lifecode.py
mempy/myemail.py
mempy/mysys.py
mempy/mytime.py
mempy/myutils.py
mempy/xlcable.py
mempy.egg-info/PKG-INFO
mempy.egg-info/SOURCES.txt
mempy.egg-info/dependency_links.txt
mempy.egg-info/top_level.txt
mempy/lib/__init__.py
mempy/lib/easygui.py
mempy/lib/transdate.py