Metadata-Version: 1.0
Name: mempy
Version: 0.1.4
Summary: MEMPIRE Python Library
Home-page: http://www.treeinsight.org/
Author: Herokims
Author-email: herokims@gmail.com
License: BSD
Platform: UNKNOWN
